{
"__comment": "Designed by MasterianoX",
"elements": [ 
{
    "from": [ 0, 4, 6.5 ],
    "to": [ 0.5, 12, 9.5 ],
    "rotation": { "origin": [ 8, 8, 8 ], "axis": "z", "angle": 0 },
    "faces": {
        "down":  { "uv": [ 16, 5, 15, 11 ], "rotation": 180, "texture": "#texture" },
        "up":    { "uv": [ 0, 5, 1, 11 ], "texture": "#texture" },
        "north": { "uv": [ 16, 5, 0, 6 ], "rotation": 270, "texture": "#texture" },
        "south": { "uv": [ 0, 11, 16, 10 ], "rotation": 90, "texture": "#texture" },
        "west":  { "uv": [ 0, 11, 16, 5 ], "rotation": 90, "texture": "#texture" },
        "east":  { "uv": [ 0, 5, 16, 11 ], "rotation": 90, "texture": "#texture" }
    }
},
{
    "from": [ 0, 4.5, 5.5 ],
    "to": [ 0.5, 11.5, 6.5 ],
    "rotation": { "origin": [ 8, 8, 8 ], "axis": "z", "angle": 0 },
    "faces": {
        "down":  { "uv": [ 15, 3, 14, 5 ], "rotation": 180, "texture": "#texture" },
        "up":    { "uv": [ 1, 3, 2, 5 ], "texture": "#texture" },
        "north": { "uv": [ 15, 3, 1, 4 ], "rotation": 270, "texture": "#texture" },
        "south": { "uv": [ 1, 5, 15, 4 ], "rotation": 90, "texture": "#texture" },
        "west":  { "uv": [ 1, 5, 15, 3 ], "rotation": 90, "texture": "#texture" },
        "east":  { "uv": [ 1, 3, 15, 5 ], "rotation": 90, "texture": "#texture" }
    }
},
{
    "from": [ 0, 4.5, 9.5 ],
    "to": [ 0.5, 11.5, 10.5 ],
    "rotation": { "origin": [ 8, 8, 8 ], "axis": "z", "angle": 0 },
    "faces": {
        "down":  { "uv": [ 15, 11, 14, 13 ], "rotation": 180, "texture": "#texture" },
        "up":    { "uv": [ 1, 11, 2, 13 ], "texture": "#texture" },
        "north": { "uv": [ 15, 11, 1, 12 ], "rotation": 270, "texture": "#texture" },
        "south": { "uv": [ 1, 13, 15, 12 ], "rotation": 90, "texture": "#texture" },
        "west":  { "uv": [ 1, 13, 15, 11 ], "rotation": 90, "texture": "#texture" },
        "east":  { "uv": [ 1, 11, 15, 13 ], "rotation": 90, "texture": "#texture" }
    }
},
{
    "from": [ 0, 5, 5 ],
    "to": [ 0.5, 11, 5.5 ],
    "rotation": { "origin": [ 8, 8, 8 ], "axis": "z", "angle": 0 },
    "faces": {
        "down":  { "uv": [ 14, 2, 13, 3 ], "rotation": 180, "texture": "#texture" },
        "up":    { "uv": [ 2, 2, 3, 3 ], "texture": "#texture" },
        "north": { "uv": [ 14, 2, 2, 3 ], "rotation": 270, "texture": "#texture" },
        "south": { "uv": [ 2, 3, 14, 2 ], "rotation": 90, "texture": "#texture" },
        "west":  { "uv": [ 2, 3, 14, 2 ], "rotation": 90, "texture": "#texture" },
        "east":  { "uv": [ 2, 2, 14, 3 ], "rotation": 90, "texture": "#texture" }
    }
},
{
    "from": [ 0, 5, 10.5 ],
    "to": [ 0.5, 11, 11 ],
    "rotation": { "origin": [ 8, 8, 8 ], "axis": "z", "angle": 0 },
    "faces": {
        "down":  { "uv": [ 14, 13, 13, 14 ], "rotation": 180, "texture": "#texture" },
        "up":    { "uv": [ 2, 13, 3, 14 ], "texture": "#texture" },
        "north": { "uv": [ 14, 13, 2, 14 ], "rotation": 270, "texture": "#texture" },
        "south": { "uv": [ 2, 14, 14, 13 ], "rotation": 90, "texture": "#texture" },
        "west":  { "uv": [ 2, 14, 14, 13 ], "rotation": 90, "texture": "#texture" },
        "east":  { "uv": [ 2, 13, 14, 14 ], "rotation": 90, "texture": "#texture" }
    }
},
{
    "from": [ 0, 5.5, 4.5 ],
    "to": [ 0.5, 10.5, 5 ],
    "rotation": { "origin": [ 8, 8, 8 ], "axis": "z", "angle": 0 },
    "faces": {
        "down":  { "uv": [ 13, 1, 12, 2 ], "rotation": 180, "texture": "#texture" },
        "up":    { "uv": [ 3, 1, 4, 2 ], "texture": "#texture" },
        "north": { "uv": [ 13, 1, 3, 2 ], "rotation": 270, "texture": "#texture" },
        "south": { "uv": [ 3, 2, 13, 1 ], "rotation": 90, "texture": "#texture" },
        "west":  { "uv": [ 3, 2, 13, 1 ], "rotation": 90, "texture": "#texture" },
        "east":  { "uv": [ 3, 1, 13, 2 ], "rotation": 90, "texture": "#texture" }
    }
},
{
    "from": [ 0, 5.5, 11 ],
    "to": [ 0.5, 10.5, 11.5 ],
    "rotation": { "origin": [ 8, 8, 8 ], "axis": "z", "angle": 0 },
    "faces": {
        "down":  { "uv": [ 13, 14, 12, 15 ], "rotation": 180, "texture": "#texture" },
        "up":    { "uv": [ 3, 14, 4, 15 ], "texture": "#texture" },
        "north": { "uv": [ 13, 14, 3, 15 ], "rotation": 270, "texture": "#texture" },
        "south": { "uv": [ 3, 15, 13, 14 ], "rotation": 90, "texture": "#texture" },
        "west":  { "uv": [ 3, 15, 13, 14 ], "rotation": 90, "texture": "#texture" },
        "east":  { "uv": [ 3, 14, 13, 15 ], "rotation": 90, "texture": "#texture" }
    }
},
{
    "from": [ 0, 6.5, 4 ],
    "to": [ 0.5, 9.5, 4.5 ],
    "rotation": { "origin": [ 8, 8, 8 ], "axis": "z", "angle": 0 },
    "faces": {
        "down":  { "uv": [ 11, 0, 10, 1 ], "rotation": 180, "texture": "#texture" },
        "up":    { "uv": [ 5, 0, 6, 1 ], "texture": "#texture" },
        "north": { "uv": [ 11, 0, 5, 1 ], "rotation": 270, "texture": "#texture" },
        "south": { "uv": [ 5, 1, 11, 0 ], "rotation": 90, "texture": "#texture" },
        "west":  { "uv": [ 5, 1, 11, 0 ], "rotation": 90, "texture": "#texture" },
        "east":  { "uv": [ 5, 0, 11, 1 ], "rotation": 90, "texture": "#texture" }
    }
},
{
    "from": [ 0, 6.5, 11.5 ],
    "to": [ 0.5, 9.5, 12 ],
    "rotation": { "origin": [ 8, 8, 8 ], "axis": "z", "angle": 0 },
    "faces": {
        "down":  { "uv": [ 11, 15, 10, 16 ], "rotation": 180, "texture": "#texture" },
        "up":    { "uv": [ 5, 15, 6, 16 ], "texture": "#texture" },
        "north": { "uv": [ 11, 15, 5, 16 ], "rotation": 270, "texture": "#texture" },
        "south": { "uv": [ 5, 16, 11, 15 ], "rotation": 90, "texture": "#texture" },
        "west":  { "uv": [ 5, 16, 11, 15 ], "rotation": 90, "texture": "#texture" },
        "east":  { "uv": [ 5, 15, 11, 16 ], "rotation": 90, "texture": "#texture" }
    }
},
{
    "from": [ 1, 6.5, 10.5 ],
    "to": [ 1.5, 9.5, 11.5 ],
    "rotation": { "origin": [ 8, 8, 8 ], "axis": "z", "angle": 0 },
    "faces": {
        "down":  { "uv": [ 1, 11, 3, 10 ], "rotation": 90, "texture": "#texture" },
        "up":    { "uv": [ 3, 5, 1, 6 ], "rotation": 90, "texture": "#texture" },
        "north": { "uv": [ 3, 5, 2, 11 ], "texture": "#texture" },
        "south": { "uv": [ 1, 5, 2, 11 ], "texture": "#texture" },
        "west":  { "uv": [ 1, 11, 3, 5 ], "rotation": 180, "texture": "#texture" },
        "east":  { "uv": [ 1, 5, 3, 11 ], "texture": "#texture" }
    }
},
{
    "from": [ 1, 9.5, 10 ],
    "to": [ 1.5, 10.5, 11 ],
    "rotation": { "origin": [ 8, 8, 8 ], "axis": "z", "angle": 0 },
    "faces": {
        "down":  { "uv": [ 2, 5, 4, 4 ], "rotation": 90, "texture": "#texture" },
        "up":    { "uv": [ 4, 3, 2, 4 ], "rotation": 90, "texture": "#texture" },
        "north": { "uv": [ 4, 3, 3, 5 ], "texture": "#texture" },
        "south": { "uv": [ 2, 3, 3, 5 ], "texture": "#texture" },
        "west":  { "uv": [ 2, 5, 4, 3 ], "rotation": 180, "texture": "#texture" },
        "east":  { "uv": [ 2, 3, 4, 5 ], "texture": "#texture" }
    }
},
{
    "from": [ 1, 5.5, 5 ],
    "to": [ 1.5, 6.5, 11 ],
    "rotation": { "origin": [ 8, 8, 8 ], "axis": "z", "angle": 0 },
    "faces": {
        "down":  { "uv": [ 2, 13, 14, 12 ], "rotation": 90, "texture": "#texture" },
        "up":    { "uv": [ 14, 11, 2, 12 ], "rotation": 90, "texture": "#texture" },
        "north": { "uv": [ 14, 11, 13, 13 ], "texture": "#texture" },
        "south": { "uv": [ 2, 11, 3, 13 ], "texture": "#texture" },
        "west":  { "uv": [ 2, 13, 14, 11 ], "rotation": 180, "texture": "#texture" },
        "east":  { "uv": [ 2, 11, 14, 13 ], "texture": "#texture" }
    }
},
{
    "from": [ 1, 10.5, 9 ],
    "to": [ 1.5, 11, 10.5 ],
    "rotation": { "origin": [ 8, 8, 8 ], "axis": "z", "angle": 0 },
    "faces": {
        "down":  { "uv": [ 3, 3, 6, 2 ], "rotation": 90, "texture": "#texture" },
        "up":    { "uv": [ 6, 2, 3, 3 ], "rotation": 90, "texture": "#texture" },
        "north": { "uv": [ 6, 2, 5, 3 ], "texture": "#texture" },
        "south": { "uv": [ 3, 2, 4, 3 ], "texture": "#texture" },
        "west":  { "uv": [ 3, 3, 6, 2 ], "rotation": 180, "texture": "#texture" },
        "east":  { "uv": [ 3, 2, 6, 3 ], "texture": "#texture" }
    }
},
{
    "from": [ 1, 6.5, 10 ],
    "to": [ 1.5, 8, 10.5 ],
    "rotation": { "origin": [ 8, 8, 8 ], "axis": "z", "angle": 0 },
    "faces": {
        "down":  { "uv": [ 3, 11, 4, 10 ], "rotation": 90, "texture": "#texture" },
        "up":    { "uv": [ 4, 8, 3, 9 ], "rotation": 90, "texture": "#texture" },
        "north": { "uv": [ 4, 8, 3, 11 ], "texture": "#texture" },
        "south": { "uv": [ 3, 8, 4, 11 ], "texture": "#texture" },
        "west":  { "uv": [ 3, 11, 4, 8 ], "rotation": 180, "texture": "#texture" },
        "east":  { "uv": [ 3, 8, 4, 11 ], "texture": "#texture" }
    }
},
{
    "from": [ 1, 5, 5.5 ],
    "to": [ 1.5, 5.5, 10.5 ],
    "rotation": { "origin": [ 8, 8, 8 ], "axis": "z", "angle": 0 },
    "faces": {
        "down":  { "uv": [ 3, 14, 13, 13 ], "rotation": 90, "texture": "#texture" },
        "up":    { "uv": [ 13, 13, 3, 14 ], "rotation": 90, "texture": "#texture" },
        "north": { "uv": [ 13, 13, 12, 14 ], "texture": "#texture" },
        "south": { "uv": [ 3, 13, 4, 14 ], "texture": "#texture" },
        "west":  { "uv": [ 3, 14, 13, 13 ], "rotation": 180, "texture": "#texture" },
        "east":  { "uv": [ 3, 13, 13, 14 ], "texture": "#texture" }
    }
},
{
    "from": [ 1, 6.5, 4.5 ],
    "to": [ 1.5, 7.5, 10 ],
    "rotation": { "origin": [ 8, 8, 8 ], "axis": "z", "angle": 0 },
    "faces": {
        "down":  { "uv": [ 4, 11, 15, 10 ], "rotation": 90, "texture": "#texture" },
        "up":    { "uv": [ 15, 9, 4, 10 ], "rotation": 90, "texture": "#texture" },
        "north": { "uv": [ 15, 9, 14, 11 ], "texture": "#texture" },
        "south": { "uv": [ 4, 9, 5, 11 ], "texture": "#texture" },
        "west":  { "uv": [ 4, 11, 15, 9 ], "rotation": 180, "texture": "#texture" },
        "east":  { "uv": [ 4, 9, 15, 11 ], "texture": "#texture" }
    }
},
{
    "from": [ 1, 11, 6.5 ],
    "to": [ 1.5, 11.5, 9.5 ],
    "rotation": { "origin": [ 8, 8, 8 ], "axis": "z", "angle": 0 },
    "faces": {
        "down":  { "uv": [ 5, 2, 11, 1 ], "rotation": 90, "texture": "#texture" },
        "up":    { "uv": [ 11, 1, 5, 2 ], "rotation": 90, "texture": "#texture" },
        "north": { "uv": [ 11, 1, 10, 2 ], "texture": "#texture" },
        "south": { "uv": [ 5, 1, 6, 2 ], "texture": "#texture" },
        "west":  { "uv": [ 5, 2, 11, 1 ], "rotation": 180, "texture": "#texture" },
        "east":  { "uv": [ 5, 1, 11, 2 ], "texture": "#texture" }
    }
},
{
    "from": [ 1, 4.5, 6.5 ],
    "to": [ 1.5, 5, 9.5 ],
    "rotation": { "origin": [ 8, 8, 8 ], "axis": "z", "angle": 0 },
    "faces": {
        "down":  { "uv": [ 5, 15, 11, 14 ], "rotation": 90, "texture": "#texture" },
        "up":    { "uv": [ 11, 14, 5, 15 ], "rotation": 90, "texture": "#texture" },
        "north": { "uv": [ 11, 14, 10, 15 ], "texture": "#texture" },
        "south": { "uv": [ 5, 14, 6, 15 ], "texture": "#texture" },
        "west":  { "uv": [ 5, 15, 11, 14 ], "rotation": 180, "texture": "#texture" },
        "east":  { "uv": [ 5, 14, 11, 15 ], "texture": "#texture" }
    }
},
{
    "from": [ 1, 7.5, 7.5 ],
    "to": [ 1.5, 8.5, 8.5 ],
    "rotation": { "origin": [ 8, 8, 8 ], "axis": "z", "angle": 0 },
    "faces": {
        "down":  { "uv": [ 7, 9, 9, 8 ], "rotation": 90, "texture": "#texture" },
        "up":    { "uv": [ 9, 7, 7, 8 ], "rotation": 90, "texture": "#texture" },
        "north": { "uv": [ 9, 7, 8, 9 ], "texture": "#texture" },
        "south": { "uv": [ 7, 7, 8, 9 ], "texture": "#texture" },
        "west":  { "uv": [ 7, 9, 9, 7 ], "rotation": 180, "texture": "#texture" },
        "east":  { "uv": [ 7, 7, 9, 9 ], "texture": "#texture" }
    }
},
{
    "from": [ 1, 10.5, 5.5 ],
    "to": [ 1.5, 11, 7 ],
    "rotation": { "origin": [ 8, 8, 8 ], "axis": "z", "angle": 0 },
    "faces": {
        "down":  { "uv": [ 10, 3, 13, 2 ], "rotation": 90, "texture": "#texture" },
        "up":    { "uv": [ 13, 2, 10, 3 ], "rotation": 90, "texture": "#texture" },
        "north": { "uv": [ 13, 2, 12, 3 ], "texture": "#texture" },
        "south": { "uv": [ 10, 2, 11, 3 ], "texture": "#texture" },
        "west":  { "uv": [ 10, 3, 13, 2 ], "rotation": 180, "texture": "#texture" },
        "east":  { "uv": [ 10, 2, 13, 3 ], "texture": "#texture" }
    }
},
{
    "from": [ 1, 9.5, 5 ],
    "to": [ 1.5, 10.5, 6 ],
    "rotation": { "origin": [ 8, 8, 8 ], "axis": "z", "angle": 0 },
    "faces": {
        "down":  { "uv": [ 12, 5, 14, 4 ], "rotation": 90, "texture": "#texture" },
        "up":    { "uv": [ 14, 3, 12, 4 ], "rotation": 90, "texture": "#texture" },
        "north": { "uv": [ 14, 3, 13, 5 ], "texture": "#texture" },
        "south": { "uv": [ 12, 3, 13, 5 ], "texture": "#texture" },
        "west":  { "uv": [ 12, 5, 14, 3 ], "rotation": 180, "texture": "#texture" },
        "east":  { "uv": [ 12, 3, 14, 5 ], "texture": "#texture" }
    }
},
{
    "from": [ 1, 7.5, 4.5 ],
    "to": [ 1.5, 8, 6 ],
    "rotation": { "origin": [ 8, 8, 8 ], "axis": "z", "angle": 0 },
    "faces": {
        "down":  { "uv": [ 12, 9, 15, 8 ], "rotation": 90, "texture": "#texture" },
        "up":    { "uv": [ 15, 8, 12, 9 ], "rotation": 90, "texture": "#texture" },
        "north": { "uv": [ 15, 8, 14, 9 ], "texture": "#texture" },
        "south": { "uv": [ 12, 8, 13, 9 ], "texture": "#texture" },
        "west":  { "uv": [ 12, 9, 15, 8 ], "rotation": 180, "texture": "#texture" },
        "east":  { "uv": [ 12, 8, 15, 9 ], "texture": "#texture" }
    }
},
{
    "from": [ 1, 8, 4.5 ],
    "to": [ 1.5, 9.5, 5.5 ],
    "rotation": { "origin": [ 8, 8, 8 ], "axis": "z", "angle": 0 },
    "faces": {
        "down":  { "uv": [ 13, 8, 15, 7 ], "rotation": 90, "texture": "#texture" },
        "up":    { "uv": [ 15, 5, 13, 6 ], "rotation": 90, "texture": "#texture" },
        "north": { "uv": [ 15, 5, 14, 8 ], "texture": "#texture" },
        "south": { "uv": [ 13, 5, 14, 8 ], "texture": "#texture" },
        "west":  { "uv": [ 13, 8, 15, 5 ], "rotation": 180, "texture": "#texture" },
        "east":  { "uv": [ 13, 5, 15, 8 ], "texture": "#texture" }
    }
},
{
    "from": [ 1, 8, 8.5 ],
    "to": [ 1.25, 9.5, 10.5 ],
    "rotation": { "origin": [ 8, 8, 8 ], "axis": "z", "angle": 0 },
    "faces": {
        "down":  { "uv": [ 3, 8, 7, 7 ], "rotation": 90, "texture": "#clock" },
        "up":    { "uv": [ 7, 5, 3, 6 ], "rotation": 90, "texture": "#clock" },
        "north": { "uv": [ 7, 5, 6, 8 ], "texture": "#clock" },
        "south": { "uv": [ 3, 5, 4, 8 ], "texture": "#clock" },
        "west":  { "uv": [ 3, 8, 7, 5 ], "rotation": 180, "texture": "#clock" },
        "east":  { "uv": [ 3, 5, 7, 8 ], "texture": "#clock" }
    }
},
{
    "from": [ 1, 9.5, 6 ],
    "to": [ 1.25, 10.5, 10 ],
    "rotation": { "origin": [ 8, 8, 8 ], "axis": "z", "angle": 0 },
    "faces": {
        "down":  { "uv": [ 4, 5, 12, 4 ], "rotation": 90, "texture": "#clock" },
        "up":    { "uv": [ 12, 3, 4, 4 ], "rotation": 90, "texture": "#clock" },
        "north": { "uv": [ 12, 3, 11, 5 ], "texture": "#clock" },
        "south": { "uv": [ 4, 3, 5, 5 ], "texture": "#clock" },
        "west":  { "uv": [ 4, 5, 12, 3 ], "rotation": 180, "texture": "#clock" },
        "east":  { "uv": [ 4, 3, 12, 5 ], "texture": "#clock" }
    }
},
{
    "from": [ 1, 7.5, 8.5 ],
    "to": [ 1.25, 8, 10 ],
    "rotation": { "origin": [ 8, 8, 8 ], "axis": "z", "angle": 0 },
    "faces": {
        "down":  { "uv": [ 4, 9, 7, 8 ], "rotation": 90, "texture": "#clock" },
        "up":    { "uv": [ 7, 8, 4, 9 ], "rotation": 90, "texture": "#clock" },
        "north": { "uv": [ 7, 8, 6, 9 ], "texture": "#clock" },
        "south": { "uv": [ 4, 8, 5, 9 ], "texture": "#clock" },
        "west":  { "uv": [ 4, 9, 7, 8 ], "rotation": 180, "texture": "#clock" },
        "east":  { "uv": [ 4, 8, 7, 9 ], "texture": "#clock" }
    }
},
{
    "from": [ 1, 10.5, 7 ],
    "to": [ 1.25, 11, 9 ],
    "rotation": { "origin": [ 8, 8, 8 ], "axis": "z", "angle": 0 },
    "faces": {
        "down":  { "uv": [ 6, 3, 10, 2 ], "rotation": 90, "texture": "#clock" },
        "up":    { "uv": [ 10, 2, 6, 3 ], "rotation": 90, "texture": "#clock" },
        "north": { "uv": [ 10, 2, 9, 3 ], "texture": "#clock" },
        "south": { "uv": [ 6, 2, 7, 3 ], "texture": "#clock" },
        "west":  { "uv": [ 6, 3, 10, 2 ], "rotation": 180, "texture": "#clock" },
        "east":  { "uv": [ 6, 2, 10, 3 ], "texture": "#clock" }
    }
},
{
    "from": [ 1, 8.5, 5.5 ],
    "to": [ 1.25, 9.5, 8.5 ],
    "rotation": { "origin": [ 8, 8, 8 ], "axis": "z", "angle": 0 },
    "faces": {
        "down":  { "uv": [ 7, 7, 13, 6 ], "rotation": 90, "texture": "#clock" },
        "up":    { "uv": [ 13, 5, 7, 6 ], "rotation": 90, "texture": "#clock" },
        "north": { "uv": [ 13, 5, 12, 7 ], "texture": "#clock" },
        "south": { "uv": [ 7, 5, 8, 7 ], "texture": "#clock" },
        "west":  { "uv": [ 7, 7, 13, 5 ], "rotation": 180, "texture": "#clock" },
        "east":  { "uv": [ 7, 5, 13, 7 ], "texture": "#clock" }
    }
},
{
    "from": [ 1, 7.5, 6 ],
    "to": [ 1.25, 8.5, 7.5 ],
    "rotation": { "origin": [ 8, 8, 8 ], "axis": "z", "angle": 0 },
    "faces": {
        "down":  { "uv": [ 9, 9, 12, 8 ], "rotation": 90, "texture": "#clock" },
        "up":    { "uv": [ 12, 7, 9, 8 ], "rotation": 90, "texture": "#clock" },
        "north": { "uv": [ 12, 7, 11, 9 ], "texture": "#clock" },
        "south": { "uv": [ 9, 7, 10, 9 ], "texture": "#clock" },
        "west":  { "uv": [ 9, 9, 12, 7 ], "rotation": 180, "texture": "#clock" },
        "east":  { "uv": [ 9, 7, 12, 9 ], "texture": "#clock" }
    }
},
{
    "from": [ 1, 8, 5.5 ],
    "to": [ 1.25, 8.5, 6 ],
    "rotation": { "origin": [ 8, 8, 8 ], "axis": "z", "angle": 0 },
    "faces": {
        "down":  { "uv": [ 12, 8, 13, 7 ], "rotation": 90, "texture": "#clock" },
        "up":    { "uv": [ 13, 7, 12, 8 ], "rotation": 90, "texture": "#clock" },
        "north": { "uv": [ 13, 7, 12, 8 ], "texture": "#clock" },
        "south": { "uv": [ 12, 7, 13, 8 ], "texture": "#clock" },
        "west":  { "uv": [ 12, 8, 13, 7 ], "rotation": 180, "texture": "#clock" },
        "east":  { "uv": [ 12, 7, 13, 8 ], "texture": "#clock" }
    }
},
{
    "from": [ 0.5, 6.5, 4 ],
    "to": [ 1, 9.5, 12 ],
    "rotation": { "origin": [ 8, 8, 8 ], "axis": "z", "angle": 0 },
    "faces": {
        "down":  { "uv": [ 0, 11, 16, 10 ], "rotation": 90, "texture": "#texture" },
        "up":    { "uv": [ 16, 5, 0, 6 ], "rotation": 90, "texture": "#texture" },
        "north": { "uv": [ 16, 5, 15, 11 ], "texture": "#texture" },
        "south": { "uv": [ 0, 5, 1, 11 ], "texture": "#texture" },
        "west":  { "uv": [ 0, 11, 16, 5 ], "rotation": 180, "texture": "#texture" },
        "east":  { "uv": [ 0, 5, 16, 11 ], "texture": "#texture" }
    }
},
{
    "from": [ 0.5, 9.5, 4.5 ],
    "to": [ 1, 10.5, 11.5 ],
    "rotation": { "origin": [ 8, 8, 8 ], "axis": "z", "angle": 0 },
    "faces": {
        "down":  { "uv": [ 1, 5, 15, 4 ], "rotation": 90, "texture": "#texture" },
        "up":    { "uv": [ 15, 3, 1, 4 ], "rotation": 90, "texture": "#texture" },
        "north": { "uv": [ 15, 3, 14, 5 ], "texture": "#texture" },
        "south": { "uv": [ 1, 3, 2, 5 ], "texture": "#texture" },
        "west":  { "uv": [ 1, 5, 15, 3 ], "rotation": 180, "texture": "#texture" },
        "east":  { "uv": [ 1, 3, 15, 5 ], "texture": "#texture" }
    }
},
{
    "from": [ 0.5, 5.5, 4.5 ],
    "to": [ 1, 6.5, 11.5 ],
    "rotation": { "origin": [ 8, 8, 8 ], "axis": "z", "angle": 0 },
    "faces": {
        "down":  { "uv": [ 1, 13, 15, 12 ], "rotation": 90, "texture": "#texture" },
        "up":    { "uv": [ 15, 11, 1, 12 ], "rotation": 90, "texture": "#texture" },
        "north": { "uv": [ 15, 11, 14, 13 ], "texture": "#texture" },
        "south": { "uv": [ 1, 11, 2, 13 ], "texture": "#texture" },
        "west":  { "uv": [ 1, 13, 15, 11 ], "rotation": 180, "texture": "#texture" },
        "east":  { "uv": [ 1, 11, 15, 13 ], "texture": "#texture" }
    }
},
{
    "from": [ 0.5, 10.5, 5 ],
    "to": [ 1, 11, 11 ],
    "rotation": { "origin": [ 8, 8, 8 ], "axis": "z", "angle": 0 },
    "faces": {
        "down":  { "uv": [ 2, 3, 14, 2 ], "rotation": 90, "texture": "#texture" },
        "up":    { "uv": [ 14, 2, 2, 3 ], "rotation": 90, "texture": "#texture" },
        "north": { "uv": [ 14, 2, 13, 3 ], "texture": "#texture" },
        "south": { "uv": [ 2, 2, 3, 3 ], "texture": "#texture" },
        "west":  { "uv": [ 2, 3, 14, 2 ], "rotation": 180, "texture": "#texture" },
        "east":  { "uv": [ 2, 2, 14, 3 ], "texture": "#texture" }
    }
},
{
    "from": [ 0.5, 5, 5 ],
    "to": [ 1, 5.5, 11 ],
    "rotation": { "origin": [ 8, 8, 8 ], "axis": "z", "angle": 0 },
    "faces": {
        "down":  { "uv": [ 2, 14, 14, 13 ], "rotation": 90, "texture": "#texture" },
        "up":    { "uv": [ 14, 13, 2, 14 ], "rotation": 90, "texture": "#texture" },
        "north": { "uv": [ 14, 13, 13, 14 ], "texture": "#texture" },
        "south": { "uv": [ 2, 13, 3, 14 ], "texture": "#texture" },
        "west":  { "uv": [ 2, 14, 14, 13 ], "rotation": 180, "texture": "#texture" },
        "east":  { "uv": [ 2, 13, 14, 14 ], "texture": "#texture" }
    }
},
{
    "from": [ 0.5, 11, 5.5 ],
    "to": [ 1, 11.5, 10.5 ],
    "rotation": { "origin": [ 8, 8, 8 ], "axis": "z", "angle": 0 },
    "faces": {
        "down":  { "uv": [ 3, 2, 13, 1 ], "rotation": 90, "texture": "#texture" },
        "up":    { "uv": [ 13, 1, 3, 2 ], "rotation": 90, "texture": "#texture" },
        "north": { "uv": [ 13, 1, 12, 2 ], "texture": "#texture" },
        "south": { "uv": [ 3, 1, 4, 2 ], "texture": "#texture" },
        "west":  { "uv": [ 3, 2, 13, 1 ], "rotation": 180, "texture": "#texture" },
        "east":  { "uv": [ 3, 1, 13, 2 ], "texture": "#texture" }
    }
},
{
    "from": [ 0.5, 4.5, 5.5 ],
    "to": [ 1, 5, 10.5 ],
    "rotation": { "origin": [ 8, 8, 8 ], "axis": "z", "angle": 0 },
    "faces": {
        "down":  { "uv": [ 3, 15, 13, 14 ], "rotation": 90, "texture": "#texture" },
        "up":    { "uv": [ 13, 14, 3, 15 ], "rotation": 90, "texture": "#texture" },
        "north": { "uv": [ 13, 14, 12, 15 ], "texture": "#texture" },
        "south": { "uv": [ 3, 14, 4, 15 ], "texture": "#texture" },
        "west":  { "uv": [ 3, 15, 13, 14 ], "rotation": 180, "texture": "#texture" },
        "east":  { "uv": [ 3, 14, 13, 15 ], "texture": "#texture" }
    }
},
{
    "from": [ 0.5, 11.5, 6.5 ],
    "to": [ 1, 12, 9.5 ],
    "rotation": { "origin": [ 8, 8, 8 ], "axis": "z", "angle": 0 },
    "faces": {
        "down":  { "uv": [ 5, 1, 11, 0 ], "rotation": 90, "texture": "#texture" },
        "up":    { "uv": [ 11, 0, 5, 1 ], "rotation": 90, "texture": "#texture" },
        "north": { "uv": [ 11, 0, 10, 1 ], "texture": "#texture" },
        "south": { "uv": [ 5, 0, 6, 1 ], "texture": "#texture" },
        "west":  { "uv": [ 5, 1, 11, 0 ], "rotation": 180, "texture": "#texture" },
        "east":  { "uv": [ 5, 0, 11, 1 ], "texture": "#texture" }
    }
},
{
    "from": [ 0.5, 4, 6.5 ],
    "to": [ 1, 4.5, 9.5 ],
    "rotation": { "origin": [ 8, 8, 8 ], "axis": "z", "angle": 0 },
    "faces": {
        "down":  { "uv": [ 5, 16, 11, 15 ], "rotation": 90, "texture": "#texture" },
        "up":    { "uv": [ 11, 15, 5, 16 ], "rotation": 90, "texture": "#texture" },
        "north": { "uv": [ 11, 15, 10, 16 ], "texture": "#texture" },
        "south": { "uv": [ 5, 15, 6, 16 ], "texture": "#texture" },
        "west":  { "uv": [ 5, 16, 11, 15 ], "rotation": 180, "texture": "#texture" },
        "east":  { "uv": [ 5, 15, 11, 16 ], "texture": "#texture" }
    }
}
]
}