[{"itemName":"Apple","description":"This block can be placed both at the top and bottom of another block\nRight click to eat","modelPath":"models/block/apple_down.json","textures":[{"name":"apple","texture":"textures/block/apple.png"}]},{"itemName":"Baked Potato","description":"Right click to eat","modelPath":"models/block/potato.json","textures":[{"name":"potato","texture":"textures/block/baked_potato.png"}]},{"itemName":"Raw Beef","description":"This block can be placed both at the top and bottom of another block\nRight click to eat","modelPath":"models/block/beef.json","textures":[{"name":"beef","texture":"textures/block/beef.png"}]},{"itemName":"Beetroot","description":"Right click to eat","modelPath":"models/block/beetroot.json","textures":[{"name":"beetroot","texture":"textures/block/beetroot.png"}]},{"itemName":"Beetroot Seeds","modelPath":"models/block/beetroot_seeds.json","textures":[{"name":"beetroot_seeds","texture":"textures/block/beetroot_seeds.png"}]},{"itemName":"Beetroot Soup","description":"Right click to eat","modelPath":"models/block/beetroot_soup.json","textures":[{"name":"beetroot_soup_still","texture":"textures/block/beetroot_soup_still.png"},{"name":"bowl","texture":"textures/block/bowl.png"}]},{"itemName":"Blaze Powder","modelPath":"models/block/blaze_powder.json","textures":[{"name":"blaze_powder","texture":"textures/block/blaze_powder.png"}]},{"itemName":"Bone","description":"Right click to grind into bone meal","modelPath":"models/block/bone.json","textures":[{"name":"bone","texture":"textures/block/bone.png"}]},{"itemName":"Book","modelPath":"models/block/book.json","textures":[{"name":"book","texture":"textures/block/book.png"}]},{"itemName":"Bowl","modelPath":"models/block/bowl.json","textures":[{"name":"bowl","texture":"textures/block/bowl.png"}]},{"itemName":"Bow","modelPath":"models/block/bow.json","textures":[{"name":"bow","texture":"textures/block/bow.png"}]},{"itemName":"Bread","description":"Right click to eat","modelPath":"models/block/bread.json","textures":[{"name":"bread","texture":"textures/block/bread.png"}]},{"itemName":"Brick","modelPath":"models/block/brick.json","textures":[{"name":"brick","texture":"textures/block/brick.png"}]},{"itemName":"Bucket","description":"This block can be placed both at the top and bottom of another block","modelPath":"models/block/bucket_down.json","textures":[{"name":"bucket","texture":"textures/block/bucket.png"}]},{"itemName":"Carrot","description":"Right click to eat\nThis block can be placed both at the top and bottom of another block","modelPath":"models/block/carrot_down.json","textures":[{"name":"carrot","texture":"textures/block/carrot.png"}]},{"itemName":"Charcoal","modelPath":"models/block/charcoal.json","textures":[{"name":"charcoal","texture":"textures/block/charcoal.png"}]},{"itemName":"Carrot on a Stick","modelPath":"models/block/carrot_on_a_stick.json","textures":[{"name":"carrot_on_a_stick","texture":"textures/block/carrot_on_a_stick.png"}]},{"itemName":"Raw Chicken","description":"This block can be placed both at the top and bottom of another block\nRight click to eat","modelPath":"models/block/chicken.json","textures":[{"name":"chicken","texture":"textures/block/chicken.png"}]},{"itemName":"Chorus Fruit","description":"This block can be placed both at the top and bottom of another block\nRight click to eat","modelPath":"models/block/chorus_fruit.json","textures":[{"name":"chorus_fruit","texture":"textures/block/chorus_fruit.png"}]},{"itemName":"Clay","modelPath":"models/block/clay_ball.json","textures":[{"name":"clay_ball","texture":"textures/block/clay_ball.png"}]},{"itemName":"Coal","modelPath":"models/block/coal.json","textures":[{"name":"coal","texture":"textures/block/coal.png"}]},{"itemName":"Steak","description":"This block can be placed both at the top and bottom of another block\nRight click to eat","modelPath":"models/block/cooked_beef.json","textures":[{"name":"cooked_beef","texture":"textures/block/cooked_beef.png"}]},{"itemName":"Cooked Chicken","description":"This block can be placed both at the top and bottom of another block\nRight click to eat","modelPath":"models/block/chicken_down.json","textures":[{"name":"chicken","texture":"textures/block/cooked_chicken.png"}]},{"itemName":"Cooked Mutton","description":"This block can be placed both at the top and bottom of another block\nRight click to eat","modelPath":"models/block/mutton_down.json","textures":[{"name":"mutton","texture":"textures/block/cooked_mutton.png"}]},{"itemName":"Cooked Porkchop","description":"This block can be placed both at the top and bottom of another block\nRight click to eat","modelPath":"models/block/beef_down.json","textures":[{"name":"beef","texture":"textures/block/cooked_porkchop.png"}]},{"itemName":"Cooked Rabbit","description":"This block can be placed both at the top and bottom of another block\nRight click to eat","modelPath":"models/block/rabbit_down.json","textures":[{"name":"rabbit","texture":"textures/block/cooked_rabbit.png"}]},{"itemName":"Cookie","description":"Right click this block with more of the same item to add to the stack","modelPath":"models/block/cookie/cookie_4.json","textures":[{"name":"cookie","texture":"textures/block/cookie.png"}]},{"itemName":"Diamond","description":"This block can be placed both at the top and bottom of another block","modelPath":"models/block/diamond.json","textures":[{"name":"diamond","texture":"textures/block/diamond.png"}]},{"itemName":"Dragon\u0027s Breath","description":"This block can be placed both at the top and bottom of another block","modelPath":"models/block/dragon_breath.json","textures":[{"name":"dragon_breath","texture":"textures/block/dragon_breath.png"}]},{"itemName":"Egg","modelPath":"models/block/egg.json","textures":[{"name":"egg","texture":"textures/block/egg.png"}]},{"itemName":"Emerald","description":"This block can be placed both at the top and bottom of another block","modelPath":"models/block/emerald.json","textures":[{"name":"emerald","texture":"textures/block/emerald.png"}]},{"itemName":"Enchanted Book","modelPath":"models/block/enchanted_book.json","textures":[{"name":"enchanted_book","texture":"textures/block/enchanted_book.png"}]},{"itemName":"Eye of Ender","modelPath":"models/block/ender_eye.json","textures":[{"name":"ender_eye","texture":"textures/block/ender_eye.png"}]},{"itemName":"Ender Pearl","modelPath":"models/block/ender_pearl.json","textures":[{"name":"ender_pearl","texture":"textures/block/ender_pearl.png"}]},{"itemName":"Bottle o\u0027 Enchanting","description":"This block can be placed both at the top and bottom of another block","modelPath":"models/block/potion_down.json","textures":[{"name":"texture","texture":"textures/block/experience_bottle.png"},{"name":"potion","texture":"textures/block/experience_bottle_still.png"}]},{"itemName":"Feather","modelPath":"models/block/feather.json","textures":[{"name":"feather","texture":"textures/block/feather.png"}]},{"itemName":"Fire Charge","description":"Right launch a fireball in the direction you\u0027re facing","modelPath":"models/block/fire_charge.json","textures":[{"name":"fire_charge","texture":"textures/block/fire_charge.png"}]},{"itemName":"Firework Rocket","description":"Right click to launch a firework","modelPath":"models/block/firework_rocket.json","textures":[{"name":"firework_rocket","texture":"textures/block/firework_rocket.png"}]},{"itemName":"Glass Bottle","description":"This block can be placed both at the top and bottom of another block","modelPath":"models/block/glass_bottle.json","textures":[{"name":"glass_bottle","texture":"textures/block/glass_bottle.png"}]},{"itemName":"Glistering Melon Slice","modelPath":"models/block/glistering_melon_slice.json","textures":[{"name":"glistering_melon_slice","texture":"textures/block/glistering_melon_slice.png"}]},{"itemName":"Gold Ingot","description":"Right click this block with more of the same item to add to the stack","modelPath":"models/block/gold_ingot.json","textures":[{"name":"gold_ingot","texture":"textures/block/gold_ingot.png"}]},{"itemName":"Golden Carrot","description":"This block can be placed both at the top and bottom of another block","modelPath":"models/block/golden_carrot.json","textures":[{"name":"golden_carrot","texture":"textures/block/golden_carrot.png"}]},{"itemName":"Iron Ingot","description":"Right click this block with more of the same item to add to the stack","modelPath":"models/block/iron_ingot.json","textures":[{"name":"iron_ingot","texture":"textures/block/iron_ingot.png"}]},{"itemName":"Lava Bucket","description":"This block can be placed both at the top and bottom of another block","modelPath":"models/block/lava_bucket.json","textures":[{"name":"lava_bucket","texture":"textures/block/lava_bucket.png"}]},{"itemName":"Leather","modelPath":"models/block/leather.json","textures":[{"name":"leather","texture":"textures/block/leather.png"}]},{"itemName":"Magma Cream","description":"This block can be placed both at the top and bottom of another block","modelPath":"models/block/magma_cream.json","textures":[{"name":"magma_cream","texture":"textures/block/magma_cream.png"}]},{"itemName":"Melon Slice","description":"Right click to eat","modelPath":"models/block/melon_slice.json","textures":[{"name":"melon_slice","texture":"textures/block/melon_slice.png"}]},{"itemName":"Milk Bucket","description":"This block can be placed both at the top and bottom of another block","modelPath":"models/block/milk_bucket.json","textures":[{"name":"milk_bucket","texture":"textures/block/milk_bucket.png"}]},{"itemName":"Mushroom Stew","description":"Right click to eat","modelPath":"models/block/mushroom_stew.json","textures":[{"name":"mushroom_stew","texture":"textures/block/mushroom_stew.png"}]},{"itemName":"Music disc","modelPath":"models/block/disc/blocks.json","textures":[{"name":"texture","texture":"textures/block/disc/blocks.png"}]},{"itemName":"Raw Mutton","description":"This block can be placed both at the top and bottom of another block\nRight click to eat","modelPath":"models/block/mutton.json","textures":[{"name":"mutton","texture":"textures/block/mutton.png"}]},{"itemName":"Nether Brick","modelPath":"models/block/nether_brick.json","textures":[{"name":"nether_brick","texture":"textures/block/nether_brick.png"}]},{"itemName":"Poisonous Potato","description":"Right click to eat","modelPath":"models/block/poisonous_potato.json","textures":[{"name":"poisonous_potato","texture":"textures/block/poisonous_potato.png"}]},{"itemName":"Popped Chorus Fruit","modelPath":"models/block/popped_chorus_fruit.json","textures":[{"name":"popped_chorus_fruit","texture":"textures/block/popped_chorus_fruit.png"}]},{"itemName":"Raw Porkchop","description":"This block can be placed both at the top and bottom of another block\nRight click to eat","modelPath":"models/block/porkchop.json","textures":[{"name":"porkchop","texture":"textures/block/porkchop.png"}]},{"itemName":"Potato","description":"Right click to eat","modelPath":"models/block/potato.json","textures":[{"name":"potato","texture":"textures/block/potato.png"}]},{"itemName":"Pumpkin Pie","description":"Right click to eat","modelPath":"models/block/pumpkin_pie.json","textures":[{"name":"pumpkin_pie","texture":"textures/block/pumpkin_pie.png"}]},{"itemName":"Raw Rabbit","description":"Right click to eat\nThis block can be placed both at the top and bottom of another block","modelPath":"models/block/rabbit.json","textures":[{"name":"rabbit","texture":"textures/block/rabbit.png"}]},{"itemName":"Rabbit Stew","description":"Right click to eat","modelPath":"models/block/rabbit_stew.json","textures":[{"name":"rabbit_stew","texture":"textures/block/rabbit_stew.png"}]},{"itemName":"Rotten Flesh","description":"Right click to eat","modelPath":"models/block/rotten_flesh.json","textures":[{"name":"rotten_flesh","texture":"textures/block/rotten_flesh.png"}]},{"itemName":"Slimeball","description":"This block can be placed both at the top and bottom of another block","modelPath":"models/block/slime_ball.json","textures":[{"name":"slime_ball","texture":"textures/block/slime_ball.png"}]},{"itemName":"Snowball","modelPath":"models/block/snowball.json","textures":[{"name":"snowball","texture":"textures/block/snowball.png"}]},{"itemName":"Spider Eye","description":"Right click to eat","modelPath":"models/block/spider_eye.json","textures":[{"name":"spider_eye","texture":"textures/block/spider_eye.png"}]},{"itemName":"Water Bucket","description":"This block can be placed both at the top and bottom of another block","modelPath":"models/block/water_bucket.json","textures":[{"name":"water_bucket","texture":"textures/block/water_bucket.png"}]},{"itemName":"Wheat","modelPath":"models/block/wheat.json","textures":[{"name":"wheat","texture":"textures/block/wheat.png"}]},{"itemName":"Book and Quill","modelPath":"models/block/writable_book.json","textures":[{"name":"writable_book","texture":"textures/block/writable_book.png"}]}]